kisee/__init__.py
kisee/__main__.py
kisee/authentication.py
kisee/emails.py
kisee/identity_provider.py
kisee/kisee.py
kisee/middlewares.py
kisee/quickstart.py
kisee/serializers.py
kisee/utils.py
kisee/views.py
kisee/providers/__init__.py
kisee/providers/demo.py
postgres_backend/__init__.py
postgres_backend/pgsql.py
kisee-21.9.0.dist-info/LICENSE
kisee-21.9.0.dist-info/METADATA
kisee-21.9.0.dist-info/WHEEL
kisee-21.9.0.dist-info/entry_points.txt
kisee-21.9.0.dist-info/top_level.txt
kisee-21.9.0.dist-info/RECORD
