Metadata-Version: 2.1
Name: kisee
Version: 21.9.0
Summary: HTTP server managing identities
Home-page: https://github.com/meltygroup/kisee
Author: Julien Palard
Author-email: julien@palard.fr
License: MIT License
Platform: UNKNOWN
Classifier: Development Status :: 5 - Production/Stable
Classifier: Intended Audience :: Information Technology
Classifier: License :: OSI Approved :: MIT License
Classifier: Natural Language :: English
Classifier: Programming Language :: Python :: 3
Classifier: Programming Language :: Python :: 3.6
Classifier: Programming Language :: Python :: 3.7
Classifier: Programming Language :: Python :: 3.8
Classifier: Programming Language :: Python :: 3.9
Requires-Python: >=3.6
License-File: LICENSE
Requires-Dist: aiocontextvars
Requires-Dist: aiohttp
Requires-Dist: aiohttp-cors
Requires-Dist: aiojobs
Requires-Dist: aiomysql
Requires-Dist: asyncpg
Requires-Dist: bcrypt
Requires-Dist: jsonpatch
Requires-Dist: pyjwt[crypto] (>=2.0.0)
Requires-Dist: requests
Requires-Dist: shortuuid
Requires-Dist: toml
Requires-Dist: werkzeug
